[
  {
    "id": 1,
    "name": "Project A",
    "description": "This is a description of Project A.",
    "status": "active",
    "start_date": "2023-01-01",
    "end_date": "",
    "group_id": 0
  },
  {
    "id": 2,
    "name": "Project B",
    "description": "This is a description of Project B.",
    "status": "active",
    "start_date": "2023-01-01",
    "end_date": "",
    "group_id": 0
  },
  {
    "id": 3,
    "name": "Project C",
    "description": "This is a description of Project C.",
    "status": "inactive",
    "start_date": "2023-01-01",
    "end_date": "2023-12-31",
    "group_id": 0
  },
  {
    "id": 4,
    "name": "test",
    "description": "",
    "status": "active",
    "start_date": "2025-08-08",
    "end_date": "",
    "group_id": 0
  },
  {
    "id": 5,
    "name": "testSync",
    "description": "",
    "status": "active",
    "start_date": "2025-08-08",
    "end_date": "",
    "group_id": 0
  },
  {
    "id": 6,
    "name": "testsYNC2",
    "description": "",
    "status": "active",
    "start_date": "2025-08-08",
    "end_date": "",
    "group_id": 0
  },
  {
    "id": 7,
    "name": "testsync3",
    "description": "",
    "status": "active",
    "start_date": "2025-08-08",
    "end_date": "",
    "group_id": 0
  },
  {
    "id": 8,
    "name": "testsync4",
    "description": "",
    "status": "active",
    "start_date": "2025-08-08",
    "end_date": "",
    "group_id": 0
  },
  {
    "id": 9,
    "name": "testsync5",
    "description": "",
    "status": "active",
    "start_date": "2025-08-08",
    "end_date": "",
    "group_id": 0
  },
  {
    "id": 10,
    "name": "testsync6",
    "description": "",
    "status": "active",
    "start_date": "2025-08-08",
    "end_date": "",
    "group_id": 0
  },
  {
    "id": 11,
    "name": "testsync7",
    "description": "",
    "status": "active",
    "start_date": "2025-08-08",
    "end_date": "",
    "group_id": 0
  },
  {
    "id": 12,
    "name": "121",
    "description": "",
    "status": "active",
    "start_date": "2025-08-10",
    "end_date": "",
    "group_id": 0
  }
]